{"enemy_id": "banshee-paul", "py/object": "sharpy.tools.opponent_data.OpponentData", "results": [{"build_used": "", "enemy_build": 0, "enemy_macro_build": 0, "enemy_race": {"py/reduce": [{"py/type": "sc2.data.Race"}, {"py/tuple": [2]}]}, "first_attacked": null, "game_duration": 617.1428571428572, "game_started": "2020-04-27T10:37:59.627825", "guid": {"hex": "6b1cbfd2583b44ff905fd81bd157bcab", "py/object": "uuid.UUID"}, "my_race": {"py/reduce": [{"py/type": "sc2.data.Race"}, {"py/tuple": [1]}]}, "py/object": "sharpy.tools.opponent_data.GameResult", "result": 1}, {"build_used": "", "enemy_build": 0, "enemy_macro_build": 0, "enemy_race": {"py/id": 3}, "first_attacked": null, "game_duration": 0.0, "game_started": "2020-04-27T10:48:15.588354", "guid": {"hex": "35eeee88fe364af4855a2fadf866abd5", "py/object": "uuid.UUID"}, "my_race": {"py/id": 5}, "py/object": "sharpy.tools.opponent_data.GameResult", "result": 1}, {"build_used": "", "enemy_build": 0, "enemy_macro_build": 0, "enemy_race": {"py/id": 3}, "first_attacked": 377.14285714285717, "game_duration": 684.1071428571429, "game_started": "2020-04-27T10:48:58.158256", "guid": {"hex": "a36597b08e874549901f805976da6497", "py/object": "uuid.UUID"}, "my_race": {"py/id": 5}, "py/object": "sharpy.tools.opponent_data.GameResult", "result": 1}, {"build_used": "", "enemy_build": 0, "enemy_macro_build": 0, "enemy_race": {"py/id": 3}, "first_attacked": null, "game_duration": 447.14285714285717, "game_started": "2020-05-18T22:43:07.726099", "guid": {"hex": "26160542a62f490f86e9d71200bd6140", "py/object": "uuid.UUID"}, "my_race": {"py/id": 5}, "py/object": "sharpy.tools.opponent_data.GameResult", "result": 1}, {"build_used": "", "enemy_build": 0, "enemy_macro_build": 0, "enemy_race": {"py/id": 3}, "first_attacked": null, "game_duration": 275.5357142857143, "game_started": "2020-05-18T22:47:31.582908", "guid": {"hex": "07bfaf7e61f94afe8ad948c5f87650d5", "py/object": "uuid.UUID"}, "my_race": {"py/id": 5}, "py/object": "sharpy.tools.opponent_data.GameResult", "result": 1}, {"build_used": "", "enemy_build": 0, "enemy_macro_build": 0, "enemy_race": {"py/id": 3}, "first_attacked": null, "game_duration": 276.25, "game_started": "2020-05-18T22:49:22.691642", "guid": {"hex": "29b3f30920294cb5abbc2f249a2ef711", "py/object": "uuid.UUID"}, "my_race": {"py/id": 5}, "py/object": "sharpy.tools.opponent_data.GameResult", "result": 1}, {"build_used": "", "enemy_build": 0, "enemy_macro_build": 0, "enemy_race": {"py/id": 3}, "first_attacked": null, "game_duration": 264.8214285714286, "game_started": "2020-05-18T23:03:41.372270", "guid": {"hex": "07a09e9d5d2b4e6a871e50a890f13190", "py/object": "uuid.UUID"}, "my_race": {"py/id": 5}, "py/object": "sharpy.tools.opponent_data.GameResult", "result": 1}, {"build_used": "", "enemy_build": 0, "enemy_macro_build": 0, "enemy_race": {"py/id": 3}, "first_attacked": 803.5714285714287, "game_duration": 867.8571428571429, "game_started": "2020-05-18T23:07:12.230723", "guid": {"hex": "831cc7349e25426ba201826b7efc01f5", "py/object": "uuid.UUID"}, "my_race": {"py/id": 5}, "py/object": "sharpy.tools.opponent_data.GameResult", "result": 1}]}